[
  {
    "name": "C",
    "urlLogo": "https://stack-icons.showwcase.com/C.png"
  },
  {
    "name": "C++",
    "urlLogo": "https://stack-icons.showwcase.com/C%2B%2B.png"
  },
  {
    "name": "C#",
    "urlLogo": "https://stack-icons.showwcase.com/C%23.png"
  },
  {
    "name": "CSS",
    "urlLogo": "https://stack-icons.showwcase.com/CSS3.png"
  },
  {
    "name": "HTML",
    "urlLogo": "https://stack-icons.showwcase.com/HTML5.png"
  },
  {
    "name": "JavaScript",
    "urlLogo": "https://stack-icons.showwcase.com/JavaScript.jpeg"
  },
  {
    "name": "Java",
    "urlLogo": "https://stack-icons.showwcase.com/Java.png"
  },
  {
    "name": "Kotlin",
    "urlLogo": "https://stack-icons.showwcase.com/Kotlin.png"
  },
  {
    "name": "Go",
    "urlLogo": "https://stack-icons.showwcase.com/Go.png"
  },
  {
    "name": "SQL",
    "urlLogo": "https://stack-icons.showwcase.com/SQL_1637837190537.png"
  }
]
